scfldr/__init__.py
scfldr/main.py
scfldr/templates/__init__.py
scfldr/templates/basic.yaml
scfldr/templates/python_package.yaml
scfldr/templates/streamlit.yaml
scfldr/templates/web.yaml
scfldr-0.1.6.dist-info/METADATA
scfldr-0.1.6.dist-info/WHEEL
scfldr-0.1.6.dist-info/entry_points.txt
scfldr-0.1.6.dist-info/licenses/LICENSE
scfldr-0.1.6.dist-info/RECORD
