Metadata-Version: 2.4
Name: scfldr
Version: 0.1.6
Summary: A command-line tool to generate folder and file structures from YAML templates
Project-URL: Homepage, https://github.com/utkarshg1/scfldr
Project-URL: Bug Tracker, https://github.com/utkarshg1/scfldr/issues
Project-URL: Documentation, https://github.com/utkarshg1/scfldr/blob/main/README.md
Author-email: utkarshg1 <gaikwadujg@gmail.com>
License: MIT
License-File: LICENSE
Keywords: cli,directory-structure,generator,project-templates,scaffolding,template
Classifier: Development Status :: 4 - Beta
Classifier: Environment :: Console
Classifier: Intended Audience :: Developers
Classifier: License :: OSI Approved :: MIT License
Classifier: Programming Language :: Python :: 3
Classifier: Programming Language :: Python :: 3.13
Classifier: Topic :: Software Development :: Build Tools
Classifier: Topic :: Software Development :: Code Generators
Requires-Python: >=3.10
Requires-Dist: aiofiles>=24.1.0
Requires-Dist: pyyaml>=6.0.2
Requires-Dist: rich>=13.0.0
Requires-Dist: typer>=0.15.4
